cdsg_plot/__init__.py
cdsg_plot/error_statistics.py
cdsg_plot/grey_bars.py
cdsg_plot/heatmap.py
cdsg_plot/modelchems.py
cdsg_plot/qcdb_plot.py
cdsg_plot/ternary.py
cdsg_plot/textables.py
cdsg_plot/thread.py
cdsg_tools-0.0.4.dist-info/licenses/LICENSE
cdsg_tools-0.0.4.dist-info/METADATA
cdsg_tools-0.0.4.dist-info/WHEEL
cdsg_tools-0.0.4.dist-info/top_level.txt
cdsg_tools-0.0.4.dist-info/zip-safe
cdsg_tools-0.0.4.dist-info/RECORD
