Metadata-Version: 2.4
Name: cdsg_tools
Version: 0.0.4
Summary: A collection of tools for writing papers and creating publication-quality figures.
Author-email: "C. David Sherrill" <sherrill@gatech.edu>, "Lori A. Burns" <lori.burns@gmail.com>, "Austin M. Wallace" <awallace43@gatech.edu>, "Caroline T. Sargent" <csargent30@gatech.edu>
License: MIT
Project-URL: Homepage, https://github.com/SherrillGroup/paper-figure-tools
Project-URL: Bug Tracker, https://github.com/SherrillGroup/paper-figure-tools/issues
Classifier: Programming Language :: Python :: 3
Classifier: License :: OSI Approved :: MIT License
Classifier: Operating System :: OS Independent
Requires-Python: >=3.8
License-File: LICENSE
Dynamic: license-file
